dccutils/__init__.py
dccutils/__version__.py
dccutils/blender.py
dccutils/exceptions.py
dccutils/guess.py
dccutils/houdini.py
dccutils/maya.py
dccutils/software.py
dccutils/unreal.py
dccutils-0.1.8.dist-info/LICENSE
dccutils-0.1.8.dist-info/METADATA
dccutils-0.1.8.dist-info/WHEEL
dccutils-0.1.8.dist-info/top_level.txt
dccutils-0.1.8.dist-info/RECORD
